aeif_lib/__init__.py
aeif_lib-0.0.3.dist-info/LICENCE
aeif_lib-0.0.3.dist-info/METADATA
aeif_lib-0.0.3.dist-info/WHEEL
aeif_lib-0.0.3.dist-info/top_level.txt
aeif_lib-0.0.3.dist-info/RECORD
