Metadata-Version: 2.1
Name: aeif-lib
Version: 0.0.3
Summary: Encrypts and decrypts image files using AES encryption in GCM mode.
Home-page: https://github.com/Pekgame/aeif-lib
Author: Pekgame
Author-email: pek795b@gmail.com
License: MIT
Classifier: License :: OSI Approved :: MIT License
Classifier: Programming Language :: Python :: 3.10
Classifier: Topic :: Security :: Cryptography
Classifier: Operating System :: OS Independent
Requires-Python: >=3.10
License-File: LICENCE
Requires-Dist: pycryptodome >=3.19.0
Provides-Extra: dev
Requires-Dist: twine >=4.0.2 ; extra == 'dev'
